LICENSE
README.md
setup.py
kaminolib/__init__.py
kaminolib/encrypt.py
kaminolib/exception.py
kaminolib.egg-info/PKG-INFO
kaminolib.egg-info/SOURCES.txt
kaminolib.egg-info/dependency_links.txt
kaminolib.egg-info/top_level.txt