Metadata-Version: 2.1
Name: kaminolib
Version: 0.0.1
Summary: kamino's persional libiaries
Home-page: https://github.com/kamino-space/kaminolib-python
Author: kamino
Author-email: kamino@imea.me
License: UNKNOWN
Platform: UNKNOWN
License-File: LICENSE
